chpypi
