Metadata-Version: 2.1
Name: chpypi
Version: 1.2.1
Summary: maker's private utils.
Home-page: https://www.itax.com
Author: maker
Author-email: 526548354@qq.com
License: MIT Licence
Keywords: pip,chpypi
Platform: any
